arrowhead_alarm/__init__.py
arrowhead_alarm/client.py
arrowhead_alarm/commands.py
arrowhead_alarm/const.py
arrowhead_alarm/consumers.py
arrowhead_alarm/exceptions.py
arrowhead_alarm/messages.py
arrowhead_alarm/session.py
arrowhead_alarm/transformers.py
arrowhead_alarm/transport.py
arrowhead_alarm/types.py
arrowhead_alarm/util.py
arrowhead_alarm-1.1.2.dist-info/METADATA
arrowhead_alarm-1.1.2.dist-info/WHEEL
arrowhead_alarm-1.1.2.dist-info/licenses/LICENSE
arrowhead_alarm-1.1.2.dist-info/RECORD
