Metadata-Version: 2.4
Name: arrowhead_alarm
Version: 1.1.2
Summary: A library for interacting with arrowhead alarm systems.
Project-URL: Repository, https://github.com/jonOriginal/arrowhead_alarm
Project-URL: Issues, https://github.com/jonOriginal/arrowhead_alarm/issues
Author-email: Jon <Jonathan@telkode.com>
License: ﻿DUAL LICENSE NOTICE
License-File: LICENSE
Keywords: alarm,arrowhead,home-automation,iot,security
Classifier: Development Status :: 4 - Beta
Classifier: Intended Audience :: Developers
Classifier: Programming Language :: Python
Classifier: Programming Language :: Python :: 3 :: Only
Classifier: Programming Language :: Python :: 3.10
Classifier: Programming Language :: Python :: 3.11
Classifier: Programming Language :: Python :: 3.12
Classifier: Programming Language :: Python :: 3.13
Classifier: Programming Language :: Python :: 3.14
Classifier: Topic :: Software Development :: Libraries
Requires-Python: <=3.14,>=3.10
